dtwr/__init__.py
dtwr/_backtrack.py
dtwr/_cli.py
dtwr/_dtw_utils.c
dtwr/_dtw_utils.cpython-36m-darwin.so
dtwr/_dtw_utils.pyx
dtwr/_globalCostMatrix.py
dtwr/countPaths.py
dtwr/data.py
dtwr/dtw.py
dtwr/dtwPlot.py
dtwr/dtw_computeCM.c
dtwr/dtw_computeCM.h
dtwr/mvm.py
dtwr/stepPattern.py
dtwr/warp.py
dtwr/warpArea.py
dtwr/window.py
dtwr/data/README.txt
dtwr/data/aami3a.csv
dtwr/data/aami3b.csv
dtwr-0.3.9.dist-info/AUTHORS.rst
dtwr-0.3.9.dist-info/LICENSE
dtwr-0.3.9.dist-info/METADATA
dtwr-0.3.9.dist-info/WHEEL
dtwr-0.3.9.dist-info/entry_points.txt
dtwr-0.3.9.dist-info/top_level.txt
dtwr-0.3.9.dist-info/RECORD
